examples/__init__.py
examples/parse_file.py
examples/bitfinex/__init__.py
examples/bitfinex/bitfinex_basic_example.py
examples/bitfinex/bitfinex_book.py
examples/cex/__init__.py
examples/cex/cex_io_private_example.py
examples/cex/cex_io_public_example.py
examples/cex/cex_io_subscribe_book.py
examples/coinbase/__init__.py
examples/coinbase/coinbase_pro_basic_example.py
examples/coinbase/coinbase_pro_private.py
examples/coinbase/coinbase_pro_write_many_books.py
examples/coinbase/coinbase_pro_write_one_book.py
examples/common/__init__.py
examples/common/book_watcher.py
examples/deribit/__init__.py
examples/deribit/check_is_connected.py
examples/deribit/deribit_basic_example.py
examples/deribit/deribit_private.py
ssc2ce/__init__.py
ssc2ce/bitfinex/__init__.py
ssc2ce/bitfinex/bitfinex.py
ssc2ce/bitfinex/l2_book.py
ssc2ce/cex/__init__.py
ssc2ce/cex/cex.py
ssc2ce/cex/l2_book.py
ssc2ce/cex/parser.py
ssc2ce/coinbase_pro/__init__.py
ssc2ce/coinbase_pro/auth.py
ssc2ce/coinbase_pro/coinbase.py
ssc2ce/coinbase_pro/l2_book.py
ssc2ce/coinbase_pro/parser.py
ssc2ce/common/__init__.py
ssc2ce/common/abstract_parser.py
ssc2ce/common/exceptions.py
ssc2ce/common/l2_book.py
ssc2ce/common/l2_book_side.py
ssc2ce/common/session.py
ssc2ce/common/utils.py
ssc2ce/deribit/__init__.py
ssc2ce/deribit/deribit.py
ssc2ce/deribit/l2_book.py
ssc2ce/deribit/parser.py
ssc2ce/factory/__init__.py
ssc2ce/factory/create_parser.py
ssc2ce/tests/__init__.py
ssc2ce/tests/cex_expected_result.py
ssc2ce/tests/cex_parser_test.py
ssc2ce/tests/coinbase_expected_result.py
ssc2ce/tests/coinbase_parser_test.py
ssc2ce/tests/deribit_expected_result.py
ssc2ce/tests/deribit_parser_test.py
ssc2ce-0.14.4.dist-info/LICENSE
ssc2ce-0.14.4.dist-info/METADATA
ssc2ce-0.14.4.dist-info/WHEEL
ssc2ce-0.14.4.dist-info/top_level.txt
ssc2ce-0.14.4.dist-info/RECORD
