Metadata-Version: 2.1
Name: ssc2ce
Version: 0.14.4
Summary: A Set of Simple Connectors for access To Cryptocurrency Exchanges
Home-page: https://github.com/olned/ssc2ce-python
Author: Oleg Nedbaylo
Author-email: olned64@gmail.com
Classifier: Programming Language :: Python :: 3.6
Classifier: License :: OSI Approved :: MIT License
Classifier: Operating System :: OS Independent
License-File: LICENSE
Requires-Dist: aiohttp
Requires-Dist: sortedcontainers
